{
  "hash": "a15a39ab",
  "configHash": "0eeb798a",
  "lockfileHash": "6e794757",
  "browserHash": "07721782",
  "optimized": {
    "react/jsx-dev-runtime": {
      "src": "../../node_modules/react/jsx-dev-runtime.js",
      "file": "react_jsx-dev-runtime.js",
      "fileHash": "47bbcb29",
      "needsInterop": true
    },
    "react": {
      "src": "../../node_modules/react/index.js",
      "file": "react.js",
      "fileHash": "386e798b",
      "needsInterop": true
    },
    "react-dom/client": {
      "src": "../../node_modules/react-dom/client.js",
      "file": "react-dom_client.js",
      "fileHash": "cf6eb380",
      "needsInterop": true
    },
    "@mantine/core": {
      "src": "../../node_modules/@mantine/core/esm/index.mjs",
      "file": "@mantine_core.js",
      "fileHash": "da11b9a2",
      "needsInterop": false
    }
  },
  "chunks": {
    "chunk-QOVZGY7A": {
      "file": "chunk-QOVZGY7A.js"
    },
    "chunk-5WQJO2FO": {
      "file": "chunk-5WQJO2FO.js"
    }
  }
}